copy_functions_and_more/LICENSE
copy_functions_and_more/README.MD
copy_functions_and_more/__init__.py
copy_functions_and_more/requirements.txt
copy_functions_and_more/thirdparty.json
copy_functions_and_more-0.10.dist-info/LICENSE.rst
copy_functions_and_more-0.10.dist-info/METADATA
copy_functions_and_more-0.10.dist-info/WHEEL
copy_functions_and_more-0.10.dist-info/top_level.txt
copy_functions_and_more-0.10.dist-info/RECORD
